rubberduck_chat/__init__.py
rubberduck_chat/configs.py
rubberduck_chat/input_handler.py
rubberduck_chat/rubberduck.py
rubberduck_chat/store.py
rubberduck_chat/utils.py
rubberduck_chat/chat_gpt/__init__.py
rubberduck_chat/chat_gpt/chat.py
rubberduck_chat/chat_gpt/credentials.py
rubberduck_chat/chat_gpt/session_store.py
rubberduck_chat/chat_gpt/setup_gpt.py
rubberduck_ai-0.6.0.dist-info/LICENSE
rubberduck_ai-0.6.0.dist-info/METADATA
rubberduck_ai-0.6.0.dist-info/WHEEL
rubberduck_ai-0.6.0.dist-info/entry_points.txt
rubberduck_ai-0.6.0.dist-info/top_level.txt
rubberduck_ai-0.6.0.dist-info/RECORD
