Metadata-Version: 2.1
Name: rubberduck-ai
Version: 0.6.0
Summary: A CLI tool for ChatGPT.
Home-page: https://github.com/hansololz/rubberduck-ai
License: GPL
Keywords: rda,openai,ChatGPT,chat
Requires-Python: >=3.5
License-File: LICENSE
Requires-Dist: inquirer (==3.1.2)
Requires-Dist: openai (==0.27.8)
Requires-Dist: pyperclip (~=1.8.2)
Requires-Dist: halo (~=0.0.31)
Requires-Dist: rich (==13.4.2)
Requires-Dist: pyreadline3 (~=3.4.1)
Requires-Dist: setuptools (==68.0.0)
Requires-Dist: aiohttp (~=3.8.4)
Requires-Dist: configparser (==6.0.0)
